README.rst
setup.cfg
setup.py
visioncpp/__init__.py
visioncpp/backend.py
visioncpp/cache.py
visioncpp/codegen.py
visioncpp/util.py
visioncpp.egg-info/PKG-INFO
visioncpp.egg-info/SOURCES.txt
visioncpp.egg-info/dependency_links.txt
visioncpp.egg-info/not-zip-safe
visioncpp.egg-info/pbr.json
visioncpp.egg-info/requires.txt
visioncpp.egg-info/top_level.txt
visioncpp/lib/include/visioncpp.hpp
visioncpp/lib/include/framework/forward_declarations.hpp
visioncpp/lib/include/framework/framework.hpp
visioncpp/lib/include/framework/device/device.hpp
visioncpp/lib/include/framework/device/sycl/device.hpp
visioncpp/lib/include/framework/device/sycl/extract_accessors.hpp
visioncpp/lib/include/framework/device/sycl/sycl_device.hpp
visioncpp/lib/include/framework/evaluator/evaluator.hpp
visioncpp/lib/include/framework/evaluator/eval_assign/eval_assign.hpp
visioncpp/lib/include/framework/evaluator/eval_assign/eval_assign_partial.hpp
visioncpp/lib/include/framework/evaluator/eval_expression/eval_expr_assign.hpp
visioncpp/lib/include/framework/evaluator/eval_expression/eval_expr_leaf_node.hpp
visioncpp/lib/include/framework/evaluator/eval_expression/eval_expr_r_binary.hpp
visioncpp/lib/include/framework/evaluator/eval_expression/eval_expr_r_unary.hpp
visioncpp/lib/include/framework/evaluator/eval_expression/eval_expr_reduction.hpp
visioncpp/lib/include/framework/evaluator/eval_expression/eval_expr_stn_filt.hpp
visioncpp/lib/include/framework/evaluator/eval_expression/eval_expr_stn_no_filt.hpp
visioncpp/lib/include/framework/evaluator/eval_expression/eval_expression.hpp
visioncpp/lib/include/framework/evaluator/load_pattern/square_pattern.hpp
visioncpp/lib/include/framework/executor/executor.hpp
visioncpp/lib/include/framework/executor/executor_subexpr_if_needed.hpp
visioncpp/lib/include/framework/executor/policy/fuse.hpp
visioncpp/lib/include/framework/executor/policy/nofuse.hpp
visioncpp/lib/include/framework/expr_convertor/expr_convertor.hpp
visioncpp/lib/include/framework/expr_convertor/leaf_count.hpp
visioncpp/lib/include/framework/expr_convertor/local_mem_count.hpp
visioncpp/lib/include/framework/expr_convertor/local_output.hpp
