Metadata-Version: 1.0
Name: visioncpp
Version: 0.1.0
Summary: Fast, GPU-accelerated computer vision and image processing
Home-page: https://github.com/ChrisCummins/visioncpp/tree/development/contrib/python
Author: Chris Cummins
Author-email: chrisc.101@gmail.com
License: Apache License, Version 2.0
Keywords: vision,image processing,gpu,sycl,computecpp,machine learning
Platform: UNKNOWN
